flask_pusher.py
FlaskPusher-1.0.1.dist-info/DESCRIPTION.rst
FlaskPusher-1.0.1.dist-info/METADATA
FlaskPusher-1.0.1.dist-info/metadata.json
FlaskPusher-1.0.1.dist-info/RECORD
FlaskPusher-1.0.1.dist-info/top_level.txt
FlaskPusher-1.0.1.dist-info/WHEEL
