Metadata-Version: 2.0
Name: FlaskPusher
Version: 1.0.1
Summary: Adds Pusher support for your Flask application.
Home-page: https://github.com/Bekt/flask-pusher
Author: Kanat Bekt
Author-email: bekt17+gh@gmail.com
License: BSD
Platform: any
Classifier: Development Status :: 4 - Beta
Classifier: Environment :: Web Environment
Classifier: Intended Audience :: Developers
Classifier: License :: OSI Approved :: BSD License
Classifier: Operating System :: OS Independent
Classifier: Programming Language :: Python
Classifier: Programming Language :: Python :: 2
Classifier: Programming Language :: Python :: 3
Classifier: Topic :: Internet :: WWW/HTTP :: Dynamic Content
Classifier: Topic :: Software Development :: Libraries :: Python Modules
Requires-Dist: Flask (>=0.10)
Requires-Dist: pusher (>=1.1)
